fhirsearchhelper/__init__.py
fhirsearchhelper/main.py
fhirsearchhelper/capabilitystatements/__init__.py
fhirsearchhelper/capabilitystatements/epic_r4_metadata_edited.json
fhirsearchhelper/helpers/__init__.py
fhirsearchhelper/helpers/capabilitystatement.py
fhirsearchhelper/helpers/conditionhelper.py
fhirsearchhelper/helpers/documenthelper.py
fhirsearchhelper/helpers/fhirfilter.py
fhirsearchhelper/helpers/gapanalysis.py
fhirsearchhelper/helpers/medicationhelper.py
fhirsearchhelper/helpers/operationoutcomehelper.py
fhirsearchhelper/models/__init__.py
fhirsearchhelper/models/models.py
fhirsearchhelper/resources/fhir_r4_search_params.json
fhirsearchhelper/resources/fhir_r4_search_params_filled_out.json
fhirsearchhelper-0.4.1.dist-info/licenses/LICENSE
fhirsearchhelper-0.4.1.dist-info/METADATA
fhirsearchhelper-0.4.1.dist-info/WHEEL
fhirsearchhelper-0.4.1.dist-info/top_level.txt
fhirsearchhelper-0.4.1.dist-info/RECORD
