Metadata-Version: 2.4
Name: fhirsearchhelper
Version: 0.4.1
Summary: A package to help with FHIR searching when needed search parameters are not available
Author-email: Andrew Stevens <andrew.stevens@gtri.gatech.edu>
Maintainer-email: Andrew Stevens <andrew.stevens@gtri.gatech.edu>
License: MIT License
Project-URL: Homepage, https://github.com/SmartChartSuite/FHIRSearchHelper
Project-URL: Bug Reports, https://github.com/SmartChartSuite/FHIRSearchHelper/issues
Project-URL: Source, https://github.com/SmartChartSuite/FHIRSearchHelper
Keywords: fhir,fhirsearching
Classifier: Development Status :: 3 - Alpha
Classifier: License :: OSI Approved :: MIT License
Classifier: Programming Language :: Python :: 3.10
Classifier: Programming Language :: Python :: 3.11
Classifier: Programming Language :: Python :: 3.12
Classifier: Operating System :: OS Independent
Requires-Python: >=3.10
License-File: LICENSE
Requires-Dist: fhir.resources==8.1.0
Requires-Dist: httpx==0.28.1
Requires-Dist: html2text==2025.4.15
Requires-Dist: fhirpathpy==2.1.0
Provides-Extra: dev
Requires-Dist: ruff==0.12.11; extra == "dev"
Requires-Dist: pytest==8.4.1; extra == "dev"
Dynamic: license-file
